sycu/__init__.py
sycu/course/Three.py
sycu/course/Two.py
sycu/course/__init__.py
sycu/course_base.py
sycu/libs/GradeTool.py
sycu/libs/__init__.py
sycu/libs/enums.py
sycu/libs/log_tools.py
sycu/libs/time_tools.py
sycu/main.py
sycu/sycu_exam/__init__.py
sycu/sycu_exam/exam.py
sycu/sycu_exam/random_grade_cplus.py
sycu/sycu_exam/random_grade_web.py
sycu/version/__init__.py
sycu/version/version_selector.py
sycu_exam-1.2.0.dist-info/LICENSE
sycu_exam-1.2.0.dist-info/METADATA
sycu_exam-1.2.0.dist-info/WHEEL
sycu_exam-1.2.0.dist-info/entry_points.txt
sycu_exam-1.2.0.dist-info/RECORD
