Metadata-Version: 2.3
Name: sycu-exam
Version: 1.2.0
Summary: sycu exam
Author: yang99love
Author-email: yang99love@126.com
Requires-Python: >=3.9,<4.0
Classifier: Programming Language :: Python :: 3
Classifier: Programming Language :: Python :: 3.9
Classifier: Programming Language :: Python :: 3.10
Classifier: Programming Language :: Python :: 3.11
Classifier: Programming Language :: Python :: 3.12
Classifier: Programming Language :: Python :: 3.13
Requires-Dist: pyfiglet (>=1.0.2,<2.0.0)
Requires-Dist: pyyaml (>=6.0.2,<7.0.0)
